myoband/__init__.py
myoband/plotting.py
myoband/analysis/__init__.py
myoband/analysis/gaussian.py
myoband/analysis/skeleton.py
myoband/simulation/__init__.py
myoband/simulation/a_band.py
myoband/simulation/randomwalk.py
myoband/simulation/slide.py
myoband/simulation/utils.py
MyoBand-1.3.dist-info/LICENSE
MyoBand-1.3.dist-info/METADATA
MyoBand-1.3.dist-info/WHEEL
MyoBand-1.3.dist-info/top_level.txt
MyoBand-1.3.dist-info/RECORD
