Metadata-Version: 2.1
Name: MyoBand
Version: 1.3
Home-page: https://github.com/hjsheehy/MyoBand
Author: Henry Joseph Sheehy
Author-email: henryjsheehy@gmail.com
License: GNU GENERAL PUBLIC LICENSE
License-File: LICENSE
Requires-Dist: numpy
Requires-Dist: scipy
Requires-Dist: matplotlib
Requires-Dist: mycolorpy
Requires-Dist: shapely
Requires-Dist: scikit-image
